{
            "id": "31",
            "name": "Tienda USD",
            "location": {
                "province": "La Habana",
                "municipality": "Boyeros",
                "lat": "23.066832",
                "long": "-82.393911"
            },
            "currency": ["CUP"],
            "phone_number": "",
            "social_media": "",
            "payment_methods": ["Efectivo ","Transferencia"],
            "product": [
                {
                    "id": "1",
                    "type": "Alimentos",
                    "name": "Azúcar 1kg",
                    "currency": ["USD"],
                    "price": "1.90",
                    "origin": "Importada"
                },
                {
                    "id": "2",
                    "type": "Alimentos",
                    "name": "Arroz 1kg",
                    "currency": ["USD"],
                    "price": "1.70",
                    "origin": "Importado"
                },
                
                {
                    "id": "4",
                    "type": "Alimentos",
                    "name": "Pechuga de Pollo 2kg",
                    "currency": ["USD"],
                    "price": "13.80",
                    "origin": "Importado"
                },
                {
                    "id": "5",
                    "type": "Alimentos",
                    "name": "Picadillo de MDM 1lb",
                    "currency": ["USD"],
                    "price": "1.00",
                    "origin": "Importado"
                },
                {
                    "id": "6",
                    "type": "Alimentos",
                    "name": "Aceite 1l",
                    "currency": ["USD"],
                    "price": "2.85",
                    "origin": "Importado"
                },

                {
                    "id": "12",
                    "type": "Bebidas alcholicas",
                    "name": "Cerveza (Unlaguer)",
                    "currency": ["USD"],
                    "price": "0.80",
                    "origin": "Importado"
                },
                {
                    "id": "13",
                    "type": "Bebidas alcholicas",
                    "name": "Whisky (Crown)",
                    "currency": ["USD"],
                    "price": "8.10",
                    "origin": "Importado"
                },
                {
                    "id": "14",
                    "type": "Bebida",
                    "name": "Refresco de Cola(Lata)",
                    "currency": ["USD"],
                    "price": "0.85",
                    "origin": "Importado"
                }
            ]
        }